boreal/__init__.py
boreal/beatles.wav
boreal/boreal.py
boreal/boreal_new.py
boreal/old_boreal.py
boreal/audio_widgets/__init__.py
boreal/audio_widgets/audio.py
boreal/audio_widgets/audio_processors.py
boreal/audio_widgets/audio_widgets.py
boreal/audio_widgets/description.html
boreal/audio_widgets/main.py
boreal-0.8.5.dist-info/AUTHORS.rst
boreal-0.8.5.dist-info/LICENSE
boreal-0.8.5.dist-info/METADATA
boreal-0.8.5.dist-info/WHEEL
boreal-0.8.5.dist-info/entry_points.txt
boreal-0.8.5.dist-info/top_level.txt
boreal-0.8.5.dist-info/RECORD
