Metadata-Version: 2.1
Name: boreal
Version: 0.8.5
Summary: Bokeh Reactive Audio Library
Home-page: https://github.com/gtzan/boreal
Author: George Tzanetakis
Author-email: gtzan@cs.uvic.ca
License: MIT license
Keywords: boreal
Classifier: Development Status :: 2 - Pre-Alpha
Classifier: Intended Audience :: Developers
Classifier: License :: OSI Approved :: MIT License
Classifier: Natural Language :: English
Classifier: Programming Language :: Python :: 3
Classifier: Programming Language :: Python :: 3.6
Classifier: Programming Language :: Python :: 3.7
Classifier: Programming Language :: Python :: 3.8
Requires-Python: >=3.6
License-File: LICENSE
License-File: AUTHORS.rst
Requires-Dist: bokeh (>=2.3.3)
Requires-Dist: ipykernel (>=5.3.4)
Requires-Dist: ipython (>=7.9.0)
Requires-Dist: notebook (>=5.3.0)
Requires-Dist: requests (>=2.27.1)
Requires-Dist: setuptools (>=61.2.0)
Requires-Dist: SoundFile (>=0.10.3.post1)
